odoo8_addon_report_xlsx-8.0.1.0.0.99.dev3-py2.7-nspkg.pth
odoo8_addon_report_xlsx-8.0.1.0.0.99.dev3.dist-info/DESCRIPTION.rst
odoo8_addon_report_xlsx-8.0.1.0.0.99.dev3.dist-info/METADATA
odoo8_addon_report_xlsx-8.0.1.0.0.99.dev3.dist-info/RECORD
odoo8_addon_report_xlsx-8.0.1.0.0.99.dev3.dist-info/WHEEL
odoo8_addon_report_xlsx-8.0.1.0.0.99.dev3.dist-info/metadata.json
odoo8_addon_report_xlsx-8.0.1.0.0.99.dev3.dist-info/namespace_packages.txt
odoo8_addon_report_xlsx-8.0.1.0.0.99.dev3.dist-info/top_level.txt
odoo_addons/report_xlsx/README.rst
odoo_addons/report_xlsx/__init__.py
odoo_addons/report_xlsx/__openerp__.py
odoo_addons/report_xlsx/i18n/report_xlsx.pot
odoo_addons/report_xlsx/models/__init__.py
odoo_addons/report_xlsx/models/ir_report.py
odoo_addons/report_xlsx/report/__init__.py
odoo_addons/report_xlsx/report/report_xlsx.py
odoo_addons/report_xlsx/static/description/icon.png
